musicxml/__init__.py
musicxml/exceptions.py
musicxml/generate_classes/__init__.py
musicxml/generate_classes/_attributes.xsd
musicxml/generate_classes/defaults/__init__.py
musicxml/generate_classes/defaults/xmlelement.py
musicxml/generate_classes/defaults/xsdattribute.py
musicxml/generate_classes/defaults/xsdcomplextype.py
musicxml/generate_classes/defaults/xsdindicator.py
musicxml/generate_classes/defaults/xsdsimpletype1.py
musicxml/generate_classes/defaults/xsdsimpletype2.py
musicxml/generate_classes/generate_all.py
musicxml/generate_classes/generate_attributes.py
musicxml/generate_classes/generate_complex_types.py
musicxml/generate_classes/generate_indicators.py
musicxml/generate_classes/generate_simple_types.py
musicxml/generate_classes/generate_xml_elements.py
musicxml/generate_classes/musicxml_4_0.xsd
musicxml/generate_classes/utils.py
musicxml/generate_classes/xml.xsd
musicxml/parser/__init__.py
musicxml/parser/_test_parser.py
musicxml/parser/parser.py
musicxml/parser/test_bach_partita_3.xml
musicxml/parser/test_bach_partita_3_created.xml
musicxml/parser/test_bach_partita_3_reduced.xml
musicxml/parser/test_bach_partita_3_reduced_created.xml
musicxml/parser/test_bach_partita_3_reordered_created.xml
musicxml/parser/test_hello_world.xml
musicxml/parser/test_hello_world_recreated.xml
musicxml/profiler/__init__.py
musicxml/profiler/parser_test.py
musicxml/profiler/parser_test.txt
musicxml/profiler/parser_test.xml
musicxml/profiler/parser_test_create.xml
musicxml/tests/__init__.py
musicxml/tests/test_utils.py
musicxml/tests/test_xmlelement/__init__.py
musicxml/tests/test_xmlelement/test_actual.xml
musicxml/tests/test_xmlelement/test_child_container.py
musicxml/tests/test_xmlelement/test_child_container.txt
musicxml/tests/test_xmlelement/test_choice.py
musicxml/tests/test_xmlelement/test_deepcopy.py
musicxml/tests/test_xmlelement/test_expected.xml
musicxml/tests/test_xmlelement/test_hello_world_actual.xml
musicxml/tests/test_xmlelement/test_hello_world_expected.xml
musicxml-1.6.1.dist-info/LICENSE
musicxml-1.6.1.dist-info/METADATA
musicxml-1.6.1.dist-info/WHEEL
musicxml-1.6.1.dist-info/RECORD
