Metadata-Version: 2.1
Name: musicxml
Version: 1.6.1
Summary: generating musicxml
Home-page: https://github.com/alexgorji/musicxml.git
License: MIT
Keywords: music,musicxml,xml
Author: Alex Gorji
Author-email: aligorji@hotmail.com
Requires-Python: >=3.9,<3.13
Classifier: License :: OSI Approved :: MIT License
Classifier: Operating System :: OS Independent
Classifier: Programming Language :: Python :: 3
Classifier: Programming Language :: Python :: 3.9
Classifier: Programming Language :: Python :: 3.10
Classifier: Programming Language :: Python :: 3.11
Classifier: Programming Language :: Python :: 3.12
Requires-Dist: verysimpletree (>=1.2,<2.0)
Project-URL: Repository, https://github.com/alexgorji/musicxml.git
